jupyter_tikz/__init__.py
jupyter_tikz/jupyter_tikz.py
jupyter_tikz-0.5.6.dist-info/LICENSE
jupyter_tikz-0.5.6.dist-info/METADATA
jupyter_tikz-0.5.6.dist-info/WHEEL
jupyter_tikz-0.5.6.dist-info/RECORD
