Metadata-Version: 2.1
Name: jupyter-tikz
Version: 0.5.6
Summary: IPython Magics for rendering TeX/TikZ in Jupyter Notebooks
License: MIT
Author: lucaslrodri
Requires-Python: >=3.10,<4.0
Classifier: Development Status :: 3 - Alpha
Classifier: Framework :: IPython
Classifier: Framework :: Jupyter
Classifier: Intended Audience :: Developers
Classifier: Intended Audience :: Science/Research
Classifier: License :: OSI Approved :: MIT License
Classifier: Natural Language :: English
Classifier: Programming Language :: Python :: 3
Classifier: Programming Language :: Python :: 3.10
Classifier: Programming Language :: Python :: 3.11
Classifier: Programming Language :: Python :: 3.12
Classifier: Topic :: Scientific/Engineering :: Visualization
Classifier: Topic :: Text Processing :: Markup :: LaTeX
Requires-Dist: ipython
Requires-Dist: jinja2 (>=3,<4)
Project-URL: Documentation, https://jupyter-tikz.readthedocs.io/
Project-URL: Homepage, https://jupyter-tikz.readthedocs.io/
Project-URL: Repository, https://github.com/lucaslrodri/jupyter-tikz/
Project-URL: Tracker, https://github.com/lucaslrodri/jupyter-tikz/issues/
